GramGetter/AUTHORS.md
GramGetter/CODE_OF_CONDUCT.md
GramGetter/GramGetter.py
GramGetter/LICENSE
GramGetter/Pipfile
GramGetter/Pipfile.lock
GramGetter/README.rst
GramGetter/__init__.py
GramGetter/instaloader.py
GramGetter/setup.py
GramGetter/test.ipynb
GramGetter/deploy/arch/PKGBUILD.template
GramGetter/deploy/arch/deploy.sh
GramGetter/deploy/arch/id_rsa_AUR.enc
GramGetter/deploy/windows/create_exe.py
GramGetter/deploy/windows/instaloader.spec
GramGetter/docs/Makefile
GramGetter/docs/README.md
GramGetter/docs/as-module.rst
GramGetter/docs/basic-usage.rst
GramGetter/docs/cli-options.rst
GramGetter/docs/codesnippets.rst
GramGetter/docs/conf.py
GramGetter/docs/contributing.rst
GramGetter/docs/favicon.ico
GramGetter/docs/index.rst
GramGetter/docs/installation.rst
GramGetter/docs/logo.png
GramGetter/docs/logo.svg
GramGetter/docs/logo_heading.png
GramGetter/docs/requirements.txt
GramGetter/docs/sphinx_autodoc_typehints.py
GramGetter/docs/sponsors.rst
GramGetter/docs/troubleshooting.rst
GramGetter/docs/_static/instaloaderdoc.css
GramGetter/docs/_static/instaloaderdoc.js
GramGetter/docs/_templates/layout.html
GramGetter/docs/_templates/page.html
GramGetter/docs/_templates/search.html
GramGetter/docs/codesnippets/113_only_one_per_user.py
GramGetter/docs/codesnippets/120_ghost_followers.py
GramGetter/docs/codesnippets/121_since_until.py
GramGetter/docs/codesnippets/194_top_x_of_user.py
GramGetter/docs/codesnippets/56_track_deleted.py
GramGetter/docs/codesnippets/615_import_firefox_session.py
GramGetter/docs/codesnippets/666_historical_hashtag_data.py
GramGetter/docs/codesnippets/README.md
GramGetter/docs/module/exceptions.rst
GramGetter/docs/module/instaloader.rst
GramGetter/docs/module/instaloadercontext.rst
GramGetter/docs/module/nodeiterator.rst
GramGetter/docs/module/structures.rst
GramGetter/instaloader/__init__.py
GramGetter/instaloader/__main__.py
GramGetter/instaloader/exceptions.py
GramGetter/instaloader/instaloader.py
GramGetter/instaloader/instaloadercontext.py
GramGetter-0.5.0.dist-info/METADATA
GramGetter-0.5.0.dist-info/WHEEL
GramGetter-0.5.0.dist-info/top_level.txt
GramGetter-0.5.0.dist-info/RECORD
